wedeliver_migrate_manager/__init__.py
wedeliver_migrate_manager/main.py
wedeliver_migrate_manager-1.5.dist-info/METADATA
wedeliver_migrate_manager-1.5.dist-info/WHEEL
wedeliver_migrate_manager-1.5.dist-info/top_level.txt
wedeliver_migrate_manager-1.5.dist-info/RECORD
